pydevccu/__init__.py
pydevccu/ccu.py
pydevccu/compat.py
pydevccu/const.py
pydevccu/converter.py
pydevccu/device_responses.py
pydevccu/proxy.py
pydevccu/server.py
pydevccu/session.py
pydevccu/device_descriptions/263_130.json
pydevccu/device_descriptions/263_131.json
pydevccu/device_descriptions/263_132.json
pydevccu/device_descriptions/263_133.json
pydevccu/device_descriptions/263_134.json
pydevccu/device_descriptions/263_135.json
pydevccu/device_descriptions/263_144.json
pydevccu/device_descriptions/263_145.json
pydevccu/device_descriptions/263_146.json
pydevccu/device_descriptions/263_147.json
pydevccu/device_descriptions/263_155.json
pydevccu/device_descriptions/263_157.json
pydevccu/device_descriptions/263_158.json
pydevccu/device_descriptions/263_160.json
pydevccu/device_descriptions/263_162.json
pydevccu/device_descriptions/263_167.json
pydevccu/device_descriptions/ALPHA-IP-RBG.json
pydevccu/device_descriptions/ASH550.json
pydevccu/device_descriptions/ASH550I.json
pydevccu/device_descriptions/BRC-H.json
pydevccu/device_descriptions/CMM.json
pydevccu/device_descriptions/ELV-SH-BS2.json
pydevccu/device_descriptions/ELV-SH-CTH.json
pydevccu/device_descriptions/ELV-SH-SW1-BAT.json
pydevccu/device_descriptions/ELV-SH-TACO.json
pydevccu/device_descriptions/ELV-SH-WSM.json
pydevccu/device_descriptions/HB-LC-Bl1-Velux.json
pydevccu/device_descriptions/HB-LC-Bl1PBU-FM.json
pydevccu/device_descriptions/HB-LC-Sw1PBU-FM.json
pydevccu/device_descriptions/HB-LC-Sw2PBU-FM.json
pydevccu/device_descriptions/HB-UNI-RGB-LED-CTRL.json
pydevccu/device_descriptions/HB-UNI-Sen-PRESS.json
pydevccu/device_descriptions/HB-UNI-Sen-TEMP-DS18B20.json
pydevccu/device_descriptions/HB-UNI-Sensor-TH-SHT75.json
pydevccu/device_descriptions/HB-UNI-Sensor-THPD-BME280.json
pydevccu/device_descriptions/HB-UNI-Sensor1.json
pydevccu/device_descriptions/HB-WDS40-THP-O.json
pydevccu/device_descriptions/HBW-LC-RGBWW-IN6-DR.json
pydevccu/device_descriptions/HBW-LC4-IN4-DR.json
pydevccu-0.2.0.dist-info/METADATA
pydevccu-0.2.0.dist-info/WHEEL
pydevccu-0.2.0.dist-info/top_level.txt
pydevccu-0.2.0.dist-info/RECORD
