Metadata-Version: 2.4
Name: pydevccu
Version: 0.2.0
Summary: Virtual HomeMatic CCU XML-RPC and JSON-RPC backend.
Home-page: https://github.com/sukramj/pydevccu
Author-email: Daniel Perna <danielperna84@gmail.com>, SukramJ <sukramj@icloud.com>
License: MIT License
Project-URL: Source Code, https://github.com/sukramj/pydevccu
Project-URL: Bug Reports, https://github.com/sukramj/pydevccu/issues
Project-URL: Changelog, https://github.com/sukramj/pydevccu/blob/master/changelog.txt
Keywords: homematic,ccu,xml-rpc,json-rpc,openccu
Classifier: Development Status :: 4 - Beta
Classifier: Intended Audience :: Developers
Classifier: License :: OSI Approved :: MIT License
Classifier: Operating System :: OS Independent
Classifier: Programming Language :: Python :: 3.13
Classifier: Programming Language :: Python :: 3.14
Classifier: Programming Language :: Python :: Free Threading :: 2 - Beta
Classifier: Framework :: AsyncIO
Classifier: Topic :: Home Automation
Classifier: Topic :: Software Development :: Libraries :: Python Modules
Classifier: Typing :: Typed
Requires-Python: >=3.13.0
Requires-Dist: aiohttp>=3.9.0
Provides-Extra: fast
Requires-Dist: orjson>=3.11.0; extra == "fast"
Provides-Extra: test
Requires-Dist: pytest>=8.0.0; extra == "test"
Requires-Dist: pytest-asyncio>=0.24.0; extra == "test"
Requires-Dist: pytest-cov>=4.0.0; extra == "test"
